README.rst
setup.py
django_email_username.egg-info/PKG-INFO
django_email_username.egg-info/SOURCES.txt
django_email_username.egg-info/dependency_links.txt
django_email_username.egg-info/requires.txt
django_email_username.egg-info/top_level.txt
emailusername/__init__.py
emailusername/admin.py
emailusername/apps.py
emailusername/models.py
emailusername/tests.py
emailusername/migrations/0001_initial.py
emailusername/migrations/__init__.py