Metadata-Version: 1.1
Name: django-email-username
Version: 0.0.3
Summary: Use email addresses in place of usernames in Django projects.
Home-page: http://github.com/acordiner/django-email-username
Author: Alister Cordiner
Author-email: alister@cordiner.net
License: GPL v2
Platform: UNKNOWN
Classifier: Development Status :: 3 - Alpha
Classifier: Environment :: Web Environment
Classifier: Framework :: Django
Classifier: Framework :: Django :: 1.8
Classifier: Intended Audience :: Developers
Classifier: License :: OSI Approved :: GNU General Public License v2 or later (GPLv2+)
Classifier: Natural Language :: English
Classifier: Operating System :: OS Independent
Classifier: Programming Language :: Python
Classifier: Programming Language :: Python :: 2
Classifier: Programming Language :: Python :: 2.7
Classifier: Topic :: Software Development :: Libraries :: Application Frameworks
